netbox_prometheus_sd/__init__.py
netbox_prometheus_sd/api/__init__.py
netbox_prometheus_sd/api/serializers.py
netbox_prometheus_sd/api/urls.py
netbox_prometheus_sd/api/utils.py
netbox_prometheus_sd/api/views.py
netbox_prometheus_sd/filtersets.py
netbox_prometheus_sd/tests/__init__.py
netbox_prometheus_sd/tests/test_api.py
netbox_prometheus_sd/tests/test_filtersets.py
netbox_prometheus_sd/tests/test_serializers.py
netbox_prometheus_sd/tests/test_utils.py
netbox_prometheus_sd/tests/utils.py
netbox_plugin_prometheus_sd-1.2.0.dist-info/LICENSE
netbox_plugin_prometheus_sd-1.2.0.dist-info/METADATA
netbox_plugin_prometheus_sd-1.2.0.dist-info/WHEEL
netbox_plugin_prometheus_sd-1.2.0.dist-info/RECORD
